COPYING.txt
MANIFEST.in
README.txt
fabfile.py
setup.py
.hg/last-message.txt
lino_patrols/__init__.py
lino_patrols/models.py
lino_patrols/settings.py
lino_patrols/setup_info.py
lino_patrols.egg-info/PKG-INFO
lino_patrols.egg-info/SOURCES.txt
lino_patrols.egg-info/dependency_links.txt
lino_patrols.egg-info/requires.txt
lino_patrols.egg-info/top_level.txt
lino_patrols/demo/__init__.py
lino_patrols/demo/manage.py
lino_patrols/demo/settings.py
lino_patrols/demo/media/cache/js/lino_000_de.js
lino_patrols/demo/media/cache/js/lino_000_en.js
lino_patrols/demo/media/cache/js/lino_900_de.js
lino_patrols/demo/media/cache/js/lino_900_fr.js
lino_patrols/fixtures/__init__.py
lino_patrols/fixtures/demo.py
lino_patrols/locale/de/LC_MESSAGES/django.mo
lino_patrols/locale/de/LC_MESSAGES/django.po
lino_patrols/locale/fr/LC_MESSAGES/django.mo
lino_patrols/locale/fr/LC_MESSAGES/django.po
lino_patrols/locale/nl/LC_MESSAGES/django.mo
lino_patrols/locale/nl/LC_MESSAGES/django.po
lino_patrols/tests/__init__.py
lino_patrols/tests/patrols_tests.py
tests/__init__.py