Metadata-Version: 1.1
Name: lino-patrols
Version: 0.0.2
Summary: A Lino application for managing patrols
Home-page: http://patrols.lino-framework.org
Author: Luc Saffre
Author-email: luc.saffre@gmail.com
License: GPL
Platform: UNKNOWN
Classifier: Programming Language :: Python
Classifier: Programming Language :: Python :: 2
Classifier: Development Status :: 1 - Planning
Classifier: Environment :: Web Environment
Classifier: Framework :: Django
Classifier: Intended Audience :: Developers
Classifier: Intended Audience :: System Administrators
Classifier: License :: OSI Approved :: GNU General Public License (GPL)
Classifier: Operating System :: OS Independent
Classifier: Topic :: Office/Business :: Scheduling
